cawsmosis/__init__.py
cawsmosis/cosmic_connect.py
cawsmosis/util.py
cawsmosis-1.5.0.dist-info/LICENSE
cawsmosis-1.5.0.dist-info/METADATA
cawsmosis-1.5.0.dist-info/WHEEL
cawsmosis-1.5.0.dist-info/entry_points.txt
cawsmosis-1.5.0.dist-info/RECORD
